{"expireTime":9007200915068024000,"key":"cfafc607d96c2412fd69f07bc734a396","val":{"name":"IMAGE_PROCESSING","inputPaths":["/Users/iris/imflos.github.io/content/posts/a-trip-to-the-french-alps/turin_torre_littoria.jpg"],"outputDir":"/Users/iris/imflos.github.io/public/static/f3ee25bf0b7eec72cc5da9df5e124f29","args":{"isLazy":false,"operations":[{"outputPath":"75985/turin_torre_littoria.jpg","args":{"width":150,"toFormat":"jpg"}},{"outputPath":"f93b5/turin_torre_littoria.jpg","args":{"width":300,"toFormat":"jpg"}},{"outputPath":"b4294/turin_torre_littoria.jpg","args":{"width":600,"toFormat":"jpg"}},{"outputPath":"8e1fc/turin_torre_littoria.jpg","args":{"width":900,"toFormat":"jpg"}},{"outputPath":"e5166/turin_torre_littoria.jpg","args":{"width":1200,"toFormat":"jpg"}},{"outputPath":"7e35d/turin_torre_littoria.jpg","args":{"width":1728,"toFormat":"jpg"}}],"pluginOptions":{"base64Width":20,"forceBase64Format":"","useMozJpeg":false,"stripMetadata":true,"lazyImageGeneration":true,"defaultQuality":50,"failOnError":true,"plugins":[]}}}}