{"expireTime":9007200897950874000,"key":"6f1e56a67c1e1e7e9ee31655a4aedba6","val":{"name":"IMAGE_PROCESSING","inputPaths":["/Users/springs/Documents/GitHub/SprLau.github.io/content/posts/managing-the-infrastructure-of-a-reusable-ecommerce-platform-with-terraform/assets/hashicorp_terraform_logo.png"],"outputDir":"/Users/springs/Documents/GitHub/SprLau.github.io/public/static/a6a61ede589d9e27f003a629c30bbe80","args":{"isLazy":false,"operations":[{"outputPath":"8a4e8/hashicorp_terraform_logo.png","args":{"width":150,"toFormat":"png"}},{"outputPath":"5a46d/hashicorp_terraform_logo.png","args":{"width":300,"toFormat":"png"}},{"outputPath":"0a47e/hashicorp_terraform_logo.png","args":{"width":600,"toFormat":"png"}},{"outputPath":"1cfc2/hashicorp_terraform_logo.png","args":{"width":900,"toFormat":"png"}},{"outputPath":"c1b63/hashicorp_terraform_logo.png","args":{"width":1200,"toFormat":"png"}},{"outputPath":"29114/hashicorp_terraform_logo.png","args":{"width":1920,"toFormat":"png"}}],"pluginOptions":{"base64Width":20,"forceBase64Format":"","useMozJpeg":false,"stripMetadata":true,"lazyImageGeneration":true,"defaultQuality":50,"failOnError":true,"plugins":[]}}}}